cv_depot/__init__.py
cv_depot/api.py
cv_depot/command.py
cv_depot/core/__init__.py
cv_depot/core/channel_map.py
cv_depot/core/color.py
cv_depot/core/enforce.py
cv_depot/core/enum.py
cv_depot/core/image.py
cv_depot/core/tools.py
cv_depot/core/types.py
cv_depot/core/video.py
cv_depot/core/viewer.py
cv_depot/ops/__init__.py
cv_depot/ops/channel.py
cv_depot/ops/draw.py
cv_depot/ops/edit.py
cv_depot/ops/filter.py
cv_depot/py.typed
cv_depot-0.12.0.dist-info/entry_points.txt
cv_depot-0.12.0.dist-info/WHEEL
cv_depot-0.12.0.dist-info/METADATA
cv_depot-0.12.0.dist-info/licenses/LICENSE
cv_depot-0.12.0.dist-info/RECORD
