Metadata-Version: 2.1
Name: cv-depot
Version: 0.12.0
Summary: Computer Vision Tools
License: MIT
Keywords: OpenEXR,EXR,openexr,exr,computer-vision,cv,image,compositing
Author-email: Alex Braun <alexander.g.braun@gmail.com>
Requires-Python: >=3.10
Classifier: Development Status :: 4 - Beta
Classifier: Intended Audience :: Developers
Classifier: License :: OSI Approved :: MIT License
Classifier: Programming Language :: Python :: 3
Classifier: Programming Language :: Python :: 3.10
Classifier: Programming Language :: Python :: 3.11
Classifier: Programming Language :: Python :: 3.12
Classifier: Programming Language :: Python :: 3.13
Classifier: Typing :: Typed
Requires-Dist: IPython
Requires-Dist: click>=8.1.3
Requires-Dist: ffmpeg-python
Requires-Dist: ipywidgets
Requires-Dist: lunchbox>=0.3.3
Requires-Dist: numpy>=2.0.2
Requires-Dist: opencv-python
Requires-Dist: openexr-tools>=0.4.0
Requires-Dist: pillow>=11.1.0
Project-URL: documentation, https://theNewFlesh.github.io/cv-depot
Project-URL: repository, https://github.com/thenewflesh/cv-depot
